mygh/__init__.py
mygh/exceptions.py
mygh/api/__init__.py
mygh/api/client.py
mygh/api/models.py
mygh/cli/__init__.py
mygh/cli/main.py
mygh/cli/repos.py
mygh/cli/search.py
mygh/cli/user.py
mygh/utils/__init__.py
mygh/utils/config.py
mygh/utils/formatting.py
mygh-0.1.4.dist-info/METADATA
mygh-0.1.4.dist-info/WHEEL
mygh-0.1.4.dist-info/entry_points.txt
mygh-0.1.4.dist-info/licenses/LICENSE
mygh-0.1.4.dist-info/RECORD
