Metadata-Version: 2.4
Name: mygh
Version: 0.1.4
Summary: A comprehensive GitHub CLI tool built with Python and Typer
Project-URL: Homepage, https://github.com/ryancheley/MyGH
Project-URL: Repository, https://github.com/ryancheley/MyGH
Project-URL: Documentation, https://github.com/ryancheley/MyGH#readme
Project-URL: Issues, https://github.com/ryancheley/MyGH/issues
Author-email: Ryan Cheley <ryan.cheley@gmail.com>
License: MIT
License-File: LICENSE
Keywords: api,cli,command-line,github,tool
Classifier: Development Status :: 4 - Beta
Classifier: Environment :: Console
Classifier: Intended Audience :: Developers
Classifier: License :: OSI Approved :: MIT License
Classifier: Operating System :: OS Independent
Classifier: Programming Language :: Python :: 3
Classifier: Programming Language :: Python :: 3.10
Classifier: Programming Language :: Python :: 3.11
Classifier: Programming Language :: Python :: 3.12
Classifier: Programming Language :: Python :: 3.13
Classifier: Topic :: Software Development :: Libraries :: Python Modules
Classifier: Topic :: Utilities
Requires-Python: >=3.10
Requires-Dist: click>=8.0.0
Requires-Dist: httpx>=0.24.0
Requires-Dist: pydantic>=2.0.0
Requires-Dist: rich>=13.0.0
Requires-Dist: tomli>=1.2.0; python_version < '3.11'
Requires-Dist: typer>=0.9.0
Provides-Extra: dev
Requires-Dist: mypy>=1.0.0; extra == 'dev'
Requires-Dist: pytest-asyncio>=0.21.0; extra == 'dev'
Requires-Dist: pytest>=7.0.0; extra == 'dev'
Requires-Dist: respx>=0.20.0; extra == 'dev'
Requires-Dist: ruff>=0.0.280; extra == 'dev'
